{
  "text": {
    "请解析这个文件": 19,
    "https": 4,
    "raw": 7,
    "githubusercontent": 3,
    "com": 2,
    "这是一个": 21,
    "xmind": 10,
    "文件链接": 15,
    "这个思维导图能帮我分析下吗": 20,
    "analyze": 0,
    "this": 9,
    "请分析这个图": 17,
    "上传这个文件": 11,
    "parse": 6,
    "the": 8,
    "mindmap": 5,
    "at": 1,
    "我上传了一个xmind文件": 12,
    "文件地址是": 14,
    "是": 16,
    "文件": 13,
    "请帮我分析这个文件": 18
  },
  "intent": {
    "upload_xmind_file": 0
  },
  "response": null,
  "action_name": {
    "action_listen": 13,
    "action_restart": 17,
    "action_session_start": 21,
    "action_default_fallback": 10,
    "action_deactivate_loop": 7,
    "action_revert_fallback_events": 18,
    "action_default_ask_affirmation": 8,
    "action_default_ask_rephrase": 9,
    "action_two_stage_fallback": 24,
    "action_unlikely_intent": 25,
    "action_back": 0,
    "action_send_text": 20,
    "action_extract_slots": 11,
    "action_cancel_flow": 2,
    "action_correct_flow_slot": 6,
    "action_clarify_flows": 3,
    "action_run_slot_rejections": 19,
    "action_clean_stack": 4,
    "action_trigger_search": 23,
    "action_trigger_chitchat": 22,
    "action_reset_routing": 16,
    "action_hangup": 12,
    "action_repeat_bot_messages": 15,
    "action_block_digression": 1,
    "action_continue_digression": 5,
    "action_parse_uploaded_xmind": 14
  },
  "action_text": null,
  "intent_response_key": null
}